config/settings.yml
querycommander/VERSION
querycommander/__init__.py
querycommander/start.py
querycommander/connectors/__init__.py
querycommander/connectors/mysqldb.py
querycommander/connectors/oracle.py
querycommander/connectors/postgres.py
querycommander/connectors/redshift.py
querycommander/connectors/selector.py
querycommander/connectors/trinodb.py
querycommander/connectors/extra_sql/mysql/columns.sql
querycommander/connectors/extra_sql/mysql/constraints.sql
querycommander/connectors/extra_sql/mysql/databases.sql
querycommander/connectors/extra_sql/mysql/function.sql
querycommander/connectors/extra_sql/mysql/functions.sql
querycommander/connectors/extra_sql/mysql/global_grants.sql
querycommander/connectors/extra_sql/mysql/grants.sql
querycommander/connectors/extra_sql/mysql/indexes.sql
querycommander/connectors/extra_sql/mysql/locks_innodb.sql
querycommander/connectors/extra_sql/mysql/locks_perf.sql
querycommander/connectors/extra_sql/mysql/procedure.sql
querycommander/connectors/extra_sql/mysql/procedures.sql
querycommander/connectors/extra_sql/mysql/schema_grants.sql
querycommander/connectors/extra_sql/mysql/sessions.sql
querycommander/connectors/extra_sql/mysql/table.sql
querycommander/connectors/extra_sql/mysql/table_info.sql
querycommander/connectors/extra_sql/mysql/tables.sql
querycommander/connectors/extra_sql/mysql/trigger.sql
querycommander/connectors/extra_sql/mysql/triggers.sql
querycommander/connectors/extra_sql/mysql/view.sql
querycommander/connectors/extra_sql/mysql/view_info.sql
querycommander/connectors/extra_sql/mysql/views.sql
querycommander/connectors/extra_sql/oracle/columns.sql
querycommander/connectors/extra_sql/oracle/constraints.sql
querycommander/connectors/extra_sql/oracle/ddl.sql
querycommander/connectors/extra_sql/oracle/function.sql
querycommander/connectors/extra_sql/oracle/functions.sql
querycommander/connectors/extra_sql/oracle/grants.sql
querycommander/connectors/extra_sql/oracle/indexes.sql
querycommander-1.0.1.dist-info/LICENSE
querycommander-1.0.1.dist-info/METADATA
querycommander-1.0.1.dist-info/WHEEL
querycommander-1.0.1.dist-info/top_level.txt
querycommander-1.0.1.dist-info/RECORD
