Metadata-Version: 2.1
Name: querycommander
Version: 1.0.1
Summary: Browser-based SQL Query Tool for Universal Database Management
Author-email: lnxusr1 <dist@querycommander.com>
License: MIT License
Project-URL: Homepage, https://querycommander.com
Project-URL: Documentation, https://docs.querycommander.com
Project-URL: Repository, https://github.com/lnxusr1/query-commander.git
Project-URL: Issues, https://github.com/lnxusr1/query-commander/issues
Project-URL: Changelog, https://docs.querycommander.com/en/latest/changelog/
Keywords: database,dba,sql,mysql,postgresql,oracle,oracldb,mariadb,redshift
Classifier: License :: OSI Approved :: MIT License
Classifier: Programming Language :: Python :: 3
Classifier: Operating System :: OS Independent
Requires-Python: >=3.6
License-File: LICENSE
Requires-Dist: cryptography
Requires-Dist: PyYAML
Provides-Extra: oracle
Requires-Dist: oracledb; extra == "oracle"
Provides-Extra: mysql
Requires-Dist: mysql-connector-python; extra == "mysql"
Provides-Extra: mariadb
Requires-Dist: mysql-connector-python; extra == "mariadb"
Provides-Extra: postgres
Requires-Dist: pg8000; extra == "postgres"
Provides-Extra: redshift
Requires-Dist: pg8000; extra == "redshift"
Provides-Extra: redis
Requires-Dist: redis; extra == "redis"
Provides-Extra: trino
Requires-Dist: trino; extra == "trino"
Provides-Extra: ldap
Requires-Dist: ldap3; extra == "ldap"
Provides-Extra: all-dbs
Requires-Dist: oracledb; extra == "all-dbs"
Requires-Dist: pg8000; extra == "all-dbs"
Requires-Dist: mysql-connector-python; extra == "all-dbs"
Requires-Dist: trino; extra == "all-dbs"
Provides-Extra: aws
Requires-Dist: boto3; extra == "aws"
Provides-Extra: all
Requires-Dist: oracledb; extra == "all"
Requires-Dist: pg8000; extra == "all"
Requires-Dist: mysql-connector-python; extra == "all"
Requires-Dist: redis; extra == "all"
Requires-Dist: boto3; extra == "all"
Requires-Dist: ldap3; extra == "all"
Requires-Dist: trino; extra == "all"
Provides-Extra: lambda
Requires-Dist: oracledb; extra == "lambda"
Requires-Dist: pg8000; extra == "lambda"
Requires-Dist: mysql-connector-python; extra == "lambda"
Requires-Dist: redis; extra == "lambda"
Requires-Dist: ldap3; extra == "lambda"
Requires-Dist: trino; extra == "lambda"
